muffin_jade.py
muffin_jade-0.0.8.dist-info/DESCRIPTION.rst
muffin_jade-0.0.8.dist-info/METADATA
muffin_jade-0.0.8.dist-info/metadata.json
muffin_jade-0.0.8.dist-info/pbr.json
muffin_jade-0.0.8.dist-info/RECORD
muffin_jade-0.0.8.dist-info/top_level.txt
muffin_jade-0.0.8.dist-info/WHEEL
