Metadata-Version: 2.0
Name: muffin-jade
Version: 0.0.8
Summary: Jade templates for Muffin Framework 
Home-page: https://github.com/klen/muffin-jade
Author: Kirill Klenov
Author-email: horneds@gmail.com
License: MIT
Keywords: asyncio,aiohttp,muffin,jade
Platform: Any
Classifier: Development Status :: 4 - Beta
Classifier: Intended Audience :: Developers
Classifier: License :: OSI Approved :: MIT License
Classifier: Natural Language :: English
Classifier: Natural Language :: Russian
Classifier: Operating System :: OS Independent
Classifier: Programming Language :: Python :: 3
Classifier: Programming Language :: Python
Classifier: Topic :: Software Development :: Libraries :: Python Modules
Classifier: Topic :: Utilities
Requires-Dist: muffin (>=0.0.99)
Requires-Dist: pyjade (==3.0.0)
